tinysim/__init__.py
tinysim/_tk_base.py
tinysim/flappy/__init__.py
tinysim/flappy/sim.js
tinysim/flappy/tk.py
tinysim/flappy/widget.py
tinysim/frogger/__init__.py
tinysim/frogger/sim.js
tinysim/frogger/tk.py
tinysim/frogger/widget.py
tinysim/mountain_car/__init__.py
tinysim/mountain_car/sim.js
tinysim/mountain_car/styles.css
tinysim/mountain_car/tk.py
tinysim/mountain_car/widget.py
tinysim/simple_amr/__init__.py
tinysim/simple_amr/example_maps.py
tinysim/simple_amr/sim.js
tinysim/simple_amr/styles.css
tinysim/simple_amr/widget.py
tinysim/topdown_driving/__init__.py
tinysim/topdown_driving/sim.js
tinysim/topdown_driving/tk.py
tinysim/topdown_driving/track_0.json
tinysim/topdown_driving/widget.py
tinysim_warp/cart_pole/__init__.py
tinysim_warp/quadruped/__init__.py
tinysim_warp/simple_quadruped/__init__.py
tinysim_warp/simple_quadruped/simple_quadruped.urdf
tinysim-0.0.2.dist-info/METADATA
tinysim-0.0.2.dist-info/WHEEL
tinysim-0.0.2.dist-info/top_level.txt
tinysim-0.0.2.dist-info/RECORD
