Metadata-Version: 2.4
Name: tinysim
Version: 0.0.2
Summary: small modular simulation environments
Author-email: Matthew Taylor <matthew.taylor.andre@gmail.com>
Project-URL: Homepage, https://github.com/MatthewAndreTaylor/TinySim
Keywords: jupyter,simulation
Classifier: Framework :: Jupyter
Classifier: Framework :: Jupyter :: JupyterLab
Classifier: Framework :: Jupyter :: JupyterLab :: 4
Classifier: Framework :: Jupyter :: JupyterLab :: Extensions
Classifier: Programming Language :: Python
Classifier: Programming Language :: Python :: 3
Classifier: Programming Language :: Python :: 3.9
Classifier: Programming Language :: Python :: 3.10
Classifier: Programming Language :: Python :: 3.11
Classifier: Programming Language :: Python :: 3.12
Classifier: Programming Language :: Python :: 3.13
Requires-Python: >=3.9
Requires-Dist: numpy
Requires-Dist: anywidget
Requires-Dist: jupyter-ui-poll
Provides-Extra: warp
Requires-Dist: warp-lang==1.8.1; extra == "warp"
